exp10it.py
updateapi.py
exp10it-2.8.72.dist-info/METADATA
exp10it-2.8.72.dist-info/WHEEL
exp10it-2.8.72.dist-info/top_level.txt
exp10it-2.8.72.dist-info/zip-safe
exp10it-2.8.72.dist-info/RECORD
