Metadata-Version: 2.1
Name: exp10it
Version: 2.8.72
Summary: This is a package about network security
Home-page: http://3xp10it.cc
Author: quanyechavshuo
Author-email: quanyechavshuo@gmail.com
License: MIT
Keywords: network security package
Classifier: License :: OSI Approved :: MIT License
Classifier: Programming Language :: Python
Classifier: Intended Audience :: Developers
Classifier: Operating System :: OS Independent
Requires-Dist: aiohttp
Requires-Dist: mechanicalsoup
Requires-Dist: bs4
Requires-Dist: selenium
Requires-Dist: colorama
Requires-Dist: requests
Requires-Dist: configparser
Requires-Dist: chardet
Requires-Dist: wget
Requires-Dist: pycryptodome
Requires-Dist: pymysql
Requires-Dist: pyperclip
Requires-Dist: html2text
